D_ff/d_ff.v
module d_flipflop(
    input d, clk,
    output reg q,
    output q_b
);

assign q_b = ~q;

always @(posedge clk)
begin
    q <= d;
end

endmodule

D_ff/d_ff_tb.v
`timescale 1ns/1ps

module d_ff_tb;

reg d, clk;
wire q, q_b;

d_flipflop uut (
    .q(q),
    .q_b(q_b),
    .d(d),
    .clk(clk)
);

// clock
initial begin
    clk = 0;
    forever #10 clk = ~clk;
end

// stimulus
initial begin
    d = 0;
    #15 d = 1;
    #20 d = 0;
    #20 d = 1;
    #20 $finish;
end

// waveform
initial begin
    $dumpfile("d_ff.vcd");
    $dumpvars(0, d_ff_tb);

    $monitor("Time=%0t clk=%b d=%b q=%b q_b=%b",
              $time, clk, d, q, q_b);
end

endmodule

D_ff/d_ff.vcd
$date
	Sun Jul 05 11:34:05 2026
$end
$version
	Icarus Verilog
$end
$timescale
	1ps
$end
$scope module d_ff_tb $end
$var wire 1 ! q_b $end
$var wire 1 " q $end
$var reg 1 # clk $end
$var reg 1 $ d $end
$scope module uut $end
$var wire 1 # clk $end
$var wire 1 $ d $end
$var wire 1 ! q_b $end
$var reg 1 " q $end
$upscope $end
$upscope $end
$enddefinitions $end
$comment Show the parameter values. $end
$dumpall
$end
#0
$dumpvars
0$
0#
x"
x!
$end
#10000
1!
0"
1#
#15000
1$
#20000
0#
#30000
0!
1"
1#
#35000
0$
#40000
0#
#50000
1!
0"
1#
#55000
1$
#60000
0#
#70000
0!
1"
1#
